{
    "00001": {
        "nome": "CSS Buy",
        "itens": {
            "00001": {
                "id": "00001",
                "nome": "Camiseta branca",
                "quantidade": 15,
                "fornecedor": "00001",
                "valor_unitario": 20.0
            },
            "00002": {
                "id": "00002",
                "nome": "Camisa preta",
                "quantidade": 1,
                "fornecedor": "00001",
                "valor_unitario": 34.0
            }
        }
    }
}